{
  "LTCUSDT": "retest-en-cours",
  "ob:USDCUSDT:ACHAT": "active",
  "ob:SOLUSDT:VENTE": "active",
  "ob:BANKUSDT:ACHAT": "active",
  "ob:ACEUSDT:ACHAT": "active",
  "ob:FDUSDUSDT:VENTE": "active",
  "ob:AAVEUSDT:ACHAT": "active",
  "ob:ALICEUSDT:ACHAT": "active",
  "wallsnap:USDCUSDT": {
    "bid": {
      "price": 1.00059,
      "qty": 44416810.0
    }
  },
  "wallsnap:BTCUSDT": {},
  "wallsnap:ETHUSDT": {},
  "wallsnap:SOLUSDT": {},
  "wallsnap:KITEUSDT": {
    "bid": {
      "price": 0.1128,
      "qty": 471483.1
    }
  },
  "wallsnap:USD1USDT": {
    "ask": {
      "price": 1.00099,
      "qty": 13061778.0
    }
  },
  "wallsnap:BANKUSDT": {},
  "wallsnap:ZECUSDT": {},
  "wallsnap:XRPUSDT": {},
  "wallsnap:BNBUSDT": {},
  "wallsnap:ACEUSDT": {},
  "wallsnap:DOGEUSDT": {},
  "wallsnap:TOWNSUSDT": {
    "bid": {
      "price": 0.00247,
      "qty": 5757094.0
    },
    "ask": {
      "price": 0.00251,
      "qty": 17374629.0
    }
  },
  "wallsnap:PEPEUSDT": {
    "ask": {
      "price": 2.95e-06,
      "qty": 122528016809.0
    }
  },
  "wallsnap:PUMPUSDT": {},
  "wallsnap:TRXUSDT": {},
  "wallsnap:ADAUSDT": {},
  "wallsnap:FDUSDUSDT": {},
  "wallsnap:NEARUSDT": {},
  "wallsnap:LTCUSDT": {
    "bid": {
      "price": 47.06,
      "qty": 2108.034
    },
    "ask": {
      "price": 47.91,
      "qty": 2128.508
    }
  },
  "wallsnap:SUIUSDT": {},
  "wallsnap:SNDKBUSDT": {},
  "wallsnap:WLDUSDT": {},
  "wallsnap:HEMIUSDT": {},
  "wallsnap:RLUSDUSDT": {
    "bid": {
      "price": 1.0006,
      "qty": 4020024.0
    },
    "ask": {
      "price": 1.001,
      "qty": 4972264.0
    }
  },
  "wallsnap:UUSDT": {},
  "wallsnap:EURUSDT": {},
  "wallsnap:XAUTUSDT": {},
  "wallsnap:PROMUSDT": {
    "bid": {
      "price": 1.91,
      "qty": 64806.8
    }
  },
  "wallsnap:OPNUSDT": {},
  "wallsnap:DEXEUSDT": {},
  "wallsnap:SPCXBUSDT": {},
  "wallsnap:XLMUSDT": {},
  "wallsnap:REUSDT": {},
  "wallsnap:LINKUSDT": {},
  "wallsnap:NIGHTUSDT": {},
  "wallsnap:AAVEUSDT": {},
  "wallsnap:TLMUSDT": {},
  "wallsnap:ENAUSDT": {
    "ask": {
      "price": 0.084,
      "qty": 1309899.14
    }
  },
  "wallsnap:ALICEUSDT": {
    "ask": {
      "price": 0.1276,
      "qty": 17171.5
    }
  }
}