{
  "BTCUSDT": "retest-en-cours",
  "ob:USDCUSDT:ACHAT": "active",
  "ob:USD1USDT:VENTE": "active",
  "ob:ZECUSDT:VENTE": "active",
  "ob:FDUSDUSDT:VENTE": "active",
  "ob:UUSDT:ACHAT": "active",
  "wallsnap:USDCUSDT": {
    "ask": {
      "price": 1.0008,
      "qty": 4439272.0
    }
  },
  "wallsnap:BTCUSDT": {},
  "wallsnap:ETHUSDT": {},
  "wallsnap:AEROUSDT": {},
  "wallsnap:KITEUSDT": {
    "bid": {
      "price": 0.1118,
      "qty": 482523.2
    }
  },
  "wallsnap:USD1USDT": {
    "ask": {
      "price": 1.00099,
      "qty": 13061778.0
    }
  },
  "wallsnap:SOLUSDT": {},
  "wallsnap:BANKUSDT": {},
  "wallsnap:DOGEUSDT": {},
  "wallsnap:XRPUSDT": {},
  "wallsnap:ZECUSDT": {
    "ask": {
      "price": 519.77,
      "qty": 2396.843
    }
  },
  "wallsnap:BNBUSDT": {},
  "wallsnap:DEXEUSDT": {
    "ask": {
      "price": 2.054,
      "qty": 1190.78
    }
  },
  "wallsnap:WLFIUSDT": {
    "bid": {
      "price": 0.0593,
      "qty": 772647.6
    }
  },
  "wallsnap:SPCXBUSDT": {},
  "wallsnap:RLUSDUSDT": {
    "bid": {
      "price": 1.0006,
      "qty": 1287156.0
    },
    "ask": {
      "price": 1.0012,
      "qty": 1531169.0
    }
  },
  "wallsnap:ZAMAUSDT": {
    "ask": {
      "price": 0.05585,
      "qty": 356588.0
    }
  },
  "wallsnap:OPNUSDT": {},
  "wallsnap:FDUSDUSDT": {
    "bid": {
      "price": 0.998,
      "qty": 1053648.0
    }
  },
  "wallsnap:TRXUSDT": {},
  "wallsnap:SNDKBUSDT": {},
  "wallsnap:EURUSDT": {
    "ask": {
      "price": 1.139,
      "qty": 183774.9
    }
  },
  "wallsnap:REUSDT": {},
  "wallsnap:ENAUSDT": {},
  "wallsnap:XAUTUSDT": {},
  "wallsnap:WLDUSDT": {},
  "wallsnap:UUSDT": {},
  "wallsnap:SUIUSDT": {},
  "wallsnap:VANAUSDT": {},
  "wallsnap:ONDOUSDT": {
    "ask": {
      "price": 0.4103,
      "qty": 175218.0
    }
  },
  "wallsnap:NEARUSDT": {},
  "wallsnap:LTCUSDT": {
    "bid": {
      "price": 46.13,
      "qty": 2940.131
    }
  },
  "wallsnap:ADAUSDT": {},
  "wallsnap:RIFUSDT": {},
  "wallsnap:PAXGUSDT": {},
  "wallsnap:SYNUSDT": {},
  "wallsnap:PEPEUSDT": {
    "ask": {
      "price": 2.8e-06,
      "qty": 63031460620.0
    }
  },
  "wallsnap:KAITOUSDT": {},
  "wallsnap:XLMUSDT": {},
  "wallsnap:AAVEUSDT": {}
}